aquacrop/__init__.py
aquacrop/core.py
aquacrop/data/CP.dat
aquacrop/data/CP.st
"aquacrop/data/CP_EC-EARTH[CP,RCP45,2021-2040]WG.dat"
"aquacrop/data/CP_EC-EARTH[CP,RCP45,2041-2060]WG.dat"
"aquacrop/data/CP_EC-EARTH[CP,RCP45,2041-2060]WG.st"
"aquacrop/data/CP_EC-EARTH[CP,RCP45,2061-2080]WG.dat"
"aquacrop/data/CP_EC-EARTH[CP,RCP85,2021-2040]WG.dat"
"aquacrop/data/CP_EC-EARTH[CP,RCP85,2041-2060]WG.dat"
"aquacrop/data/CP_EC-EARTH[CP,RCP85,2061-2080]WG.dat"
aquacrop/data/MaunaLoaCO2.txt
aquacrop/data/__init__.py
aquacrop/data/brussels_climate.txt
aquacrop/data/champion_climate.txt
aquacrop/data/hyderabad_climate.txt
aquacrop/data/paddyrice_hyderabad_matlab.txt
aquacrop/data/paddyrice_hyderabad_windows.OUT
aquacrop/data/potato_matlab.txt
aquacrop/data/potato_windows.OUT
aquacrop/data/tunis_climate.txt
aquacrop/data/tunis_test_1_SandyLoam_matlab.txt
aquacrop/data/tunis_test_1_SandyLoam_windows.OUT
aquacrop/data/tunis_test_1_matlab.txt
aquacrop/data/tunis_test_1_windows.OUT
aquacrop/data/tunis_test_2_long_matlab.txt
aquacrop/data/tunis_test_2_long_windows.OUT
aquacrop/data/tunis_test_3_30taw_matlab.txt
aquacrop/data/tunis_test_3_30taw_windows.OUT
aquacrop/data/tunis_test_6_matlab.txt
aquacrop/data/tunis_test_6_windows.OUT
aquacrop/data/tunis_wheat_gw15_matlab.txt
aquacrop/data/tunis_wheat_gw15_windows.OUT
aquacrop/entities/__init__.py
aquacrop/entities/clockStruct.py
aquacrop/entities/co2.py
aquacrop/entities/crop.py
aquacrop/entities/fieldManagement.py
aquacrop/entities/groundWater.py
aquacrop/entities/initParamVariables.py
aquacrop/entities/inititalWaterContent.py
aquacrop/entities/irrigationManagement.py
aquacrop/entities/moistureDepletion.py
aquacrop/entities/output.py
aquacrop/entities/paramStruct.py
aquacrop/entities/rootZoneWaterContent.py
aquacrop/entities/soil.py
aquacrop/entities/soilProfile.py
aquacrop/entities/temperatureStressCoefficients.py
aquacrop/entities/totalAvailableWater.py
aquacrop/entities/waterEvaporation.py
aquacrop_pacs27-0.0.31.dist-info/LICENSE
aquacrop_pacs27-0.0.31.dist-info/METADATA
aquacrop_pacs27-0.0.31.dist-info/WHEEL
aquacrop_pacs27-0.0.31.dist-info/top_level.txt
aquacrop_pacs27-0.0.31.dist-info/RECORD
