Metadata-Version: 2.1
Name: aquacrop-pacs27
Version: 0.0.31
Summary: Agronomic Model
Home-page: https://github.com/user/sampleproject
Author: Francisco Puig Pérez-Barquero
Author-email: pacopuig1995@gmail.com
License: UNKNOWN
Project-URL: Bug Tracker, https://github.com/user/sampleproject/issues
Keywords: aquacrop,agriculture
Platform: UNKNOWN
Classifier: Programming Language :: Python :: 3.8
Classifier: Programming Language :: Python :: 3.9
Classifier: Programming Language :: Python :: 3.10
Classifier: License :: OSI Approved :: MIT License
Classifier: Operating System :: MacOS
Classifier: Operating System :: Microsoft
Classifier: Operating System :: POSIX :: Linux
Requires-Python: >=3.6
License-File: LICENSE
Requires-Dist: numba (==0.55.0)
Requires-Dist: numpy (<1.22.0,>=1.18.0)
Requires-Dist: pandas (>=1.4.0)
